Workbook

Sheet 1_Public Data Inputs
A1: Company Name | B1: Raytheon Technologies
A2: Ticker | B2: RTX
A4: Current Share Price | B4: 184.42
A5: Market Cap | B5: 247270000000
A6: Entreprise Value (EV) | B6: 282010000000
A7: Shares Outstanding | B7: 1340000000
A8: Total Debt | B8: 40710000000
A9: Cash on Hand | B9: 5970000000
A11: Revenue (TTM) | B11: 85990000000
A12: EBIT Margin (TTM) | B12: =C12/B11 -> 0.10251192 | C12: 8815000000
A13: Free Cash Flow (TTM) | B13: 4730000000
A16: Beta (5y) | B16: 0.55
A17: Risk Free Rate (10y Treasury) | B17: 0.0412
A18: Market Risk Premium (Assumption) | B18: 0.055
A21: Source Links

Sheet 2_Assumptions
A1: Forecast Years | B1: FY1 | C1: FY2 | D1: FY3 | E1: FY4 | F1: FY5
A4: Base Case: Revenue Growth | B4: 0.04 | C4: 0.04 | D4: 0.04 | E4: 0.04 | F4: 0.04
A5: Rate Shock Scenario (Higher WACC) | B5: 0.02 | C5: 0.02 | D5: 0.02 | E5: 0.02 | F5: 0.02
A6: Budget Normalization Scenario | B6: 0.01 | C6: 0.01 | D6: 0.01 | E6: 0.01 | F6: 0.01
A8: EBIT Margin - Base | B8: 0.103 | C8: 0.104 | D8: 0.105 | E8: 0.106 | F8: 0.107
A9: EBIT Margin - Stress Case | B9: 0.095 | C9: 0.095 | D9: 0.094 | E9: 0.094 | F9: 0.093
A12: Risk-Free Rate | B12: 0.0412
A13: Beta | B13: 0.44
A14: Market Risk Premium | B14: 0.05
A15: Cost of Debt (assumption) | B15: 5.0%-6.0%
A16: Tax Rate | B16: 0.21
A18: CapEx as % of Revenue | B18: 0.03
A19: Deprecation as % of Revenue | B19: 0.025
A20: Change in Working Capital | B20: 0.005
A22: Terminal Growth (g) | B22: =B27 -> 0.015
A24: Active Revenue Growth | B24: =IF('7_Scenarios'!$B$2="Base",'7_Scenarios'!B7,IF('7_Scenarios'!$B$2="Upside",'7_Scenarios'!C7,'7_Scenarios'!D7)) -> 0.06
A25: Active EBIT Margin | B25: =IF('7_Scenarios'!$B$2="Base",'7_Scenarios'!B8,IF('7_Scenarios'!$B$2="Upside",'7_Scenarios'!C8,'7_Scenarios'!D8)) -> 0.103
A26: Active WACC | B26: =IF('7_Scenarios'!$B$2="Base",'7_Scenarios'!B9,IF('7_Scenarios'!$B$2="Upside",'7_Scenarios'!C9,'7_Scenarios'!D9)) -> 0.0698
A27: Active Terminal Growth | B27: =IF('7_Scenarios'!$B$2="Base",'7_Scenarios'!B10,IF('7_Scenarios'!$B$2="Upside",'7_Scenarios'!C10,'7_Scenarios'!D10)) -> 0.015
A28: Active CapEx % | B28: =IF('7_Scenarios'!$B$2="Base", '7_Scenarios'!B11, IF('7_Scenarios'!$B$2="Upside", '7_Scenarios'!C11, IF('7_Scenarios'!$B$2="Downside", '7_Scenarios'!D11, " "))) -> 0.03

Sheet 3_Forecast Build 
B1: FY1 | C1: FY2 | D1: FY3 | E1: FY4 | F1: FY5
A3: Starting Revenue (TTM) | B3: ='1_Public Data Inputs'!B11 -> 85990000000 | C3: =B5 -> 91149400000 | D3: =C5 -> 96618364000 | E3: =D5 -> 102415465840 | F3: =E5 -> 108560393790
A4: Revenue Growth Assumption | B4: ='2_Assumptions'!$B$24 -> 0.06 | C4: ='2_Assumptions'!$B$24 -> 0.06 | D4: ='2_Assumptions'!$B$24 -> 0.06 | E4: ='2_Assumptions'!$B$24 -> 0.06 | F4: ='2_Assumptions'!$B$24 -> 0.06
A5: Projected Revenue | B5: =B3*(1+B4) -> 91149400000 | C5: =C3*(1+C4) -> 96618364000 | D5: =D3*(1+D4) -> 102415465840 | E5: =E3*(1+E4) -> 108560393790 | F5: =F3*(1+F4) -> 115074017418
A8: EBIT Margin (Base Case) | B8: ='2_Assumptions'!B25 -> 0.103 | C8: =B8+0.1% -> 0.104 | D8: =C8+0.1% -> 0.105 | E8: =D8+0.1% -> 0.106 | F8: =E8+0.1% -> 0.107
A9: EBIT (Base Case) | B9: =B5*B8 -> 9388388200 | C9: =C5*C8 -> 10048309856 | D9: =D5*D8 -> 10753623913 | E9: =E5*E8 -> 11507401742 | F9: =F5*F8 -> 12312919864
A11: Tax Rate | B11: ='2_Assumptions'!$B$16 -> 0.21 | C11: ='2_Assumptions'!$B$16 -> 0.21 | D11: ='2_Assumptions'!$B$16 -> 0.21 | E11: ='2_Assumptions'!$B$16 -> 0.21 | F11: ='2_Assumptions'!$B$16 -> 0.21
A12: NOPAT | B12: =B9*(1-B11) -> 7416826678 | C12: =C9*(1-C11) -> 7938164786 | D12: =D9*(1-D11) -> 8495362891 | E12: =E9*(1-E11) -> 9090847376 | F12: =F9*(1-F11) -> 9727206692
A14: Depreciation (from assumptions) | B14: =B5*'2_Assumptions'!$B$19 -> 2278735000 | C14: =C5*'2_Assumptions'!$B$19 -> 2415459100 | D14: =D5*'2_Assumptions'!$B$19 -> 2560386646 | E14: =E5*'2_Assumptions'!$B$19 -> 2714009845 | F14: =F5*'2_Assumptions'!$B$19 -> 2876850435
A15: CapEx (from assumptions) | B15: =B5*'2_Assumptions'!B28 -> 2734482000 | C15: =C5*'2_Assumptions'!$B$28 -> 2898550920 | D15: =D5*'2_Assumptions'!$B$28 -> 3072463975 | E15: =E5*'2_Assumptions'!$B$28 -> 3256811814 | F15: =F5*'2_Assumptions'!$B$28 -> 3452220523
A16: Change in Working Capital | B16: =B5*'2_Assumptions'!$B$20 -> 455747000 | C16: =C5*'2_Assumptions'!$B$20 -> 483091820 | D16: =D5*'2_Assumptions'!$B$20 -> 5.1207733e+08 | E16: =E5*'2_Assumptions'!$B$28 -> 3256811814 | F16: =F5*'2_Assumptions'!$B$20 -> 5.7537009e+08
A17: Unlevered Free Cash Flow (FCFF) | B17: =B12+B14-B15-B16 -> 6505332678 | C17: =C12+C14-C15-C16 -> 6971981146 | D17: =D12+D14-D15-D16 -> 7471208233 | E17: =E12+E14-E15-E16 -> 5291233593 | F17: =F12+F14-F15-F16 -> 8576466518

Sheet 4_WACC
A1: Inputs
A2: Risk-Free Rate (RFR) | B2: ='1_Public Data Inputs'!B17 -> 0.0412
A3: Beta (5y Monthly) | B3: ='1_Public Data Inputs'!B16 -> 0.55
A4: Market Risk Premium (MRP) | B4: ='1_Public Data Inputs'!B18 -> 0.055
A5: Cost of Equity (CAPM) | B5: =B2+(B3*B4) -> 0.07145
A7: Cost of Debt
A8: Pre-Tax Cost of Debt (assumed) | B8: 0.0625
A9: Tax Rate | B9: ='2_Assumptions'!B16 -> 0.21
A10: After-Tax Cost of Debt | B10: =B8*(1-B9) -> 0.049375
A12: Capital Structure Weight
A13: Market Cap | B13: ='1_Public Data Inputs'!B5 -> 247270000000
A14: Total Debt | B14: ='1_Public Data Inputs'!B8 -> 40710000000
A15: Entreprise Value | B15: =B13+B14-'1_Public Data Inputs'!B9 -> 282010000000
A16: Weight of Equity | B16: =B13/B15 -> 0.87681288
A17: Weight of Debt | B17: =B14/B15 -> 0.14435658
A19: WACC | B19: ='2_Assumptions'!B26 -> 0.0698

Sheet 5_DCF Valuation
A1: Year | B1: FY1 | C1: FY2 | D1: FY3 | E1: FY4 | F1: FY5 | G1: Terminal Value
A3: Unlevered Free Cash Flow (FCFF) | B3: ='3_Forecast Build '!B17 -> 6505332678 | C3: ='3_Forecast Build '!C17 -> 6971981146 | D3: ='3_Forecast Build '!D17 -> 7471208233 | E3: ='3_Forecast Build '!E17 -> 5291233593 | F3: ='3_Forecast Build '!F17 -> 8576466518 | G3: ='3_Forecast Build '!F17 * (1 + '2_Assumptions'!$B$22) / ('4_WACC'!$B$19 - '2_Assumptions'!$B$22) -> 158852436422
A5: Discount Factor | B5: =1/(1+'4_WACC'!$B$19)^1 -> 0.93475416 | C5: =1/(1+'4_WACC'!$B$19)^2 -> 0.87376534 | D5: =1/(1+'4_WACC'!$B$19)^3 -> 0.81675579 | E5: =1/(1+'4_WACC'!$B$19)^4 -> 0.76346587 | F5: =1/(1+'4_WACC'!$B$19)^5 -> 0.7136529 | G5: =1/(1+'4_WACC'!$B$19)^5 -> 0.7136529
A7: Present Value of FCFF | B7: =B3*B5 -> 6080886781 | C7: =C3*C5 -> 6091875470 | D7: =D3*D5 -> 6102152547 | E7: =E3*E5 -> 4039676246 | F7: =F3*F5 -> 6120620164 | G7: =G3*G5 -> 113365501213
A8: PV of Terminal Value | G8: =G3 / (1 + '4_WACC'!$B$19)^5 -> 113365501213
A9: Enterprise Value (DCF) | B9: =SUM(B7:F7)+G7 -> 141800712420
A11: Enterprise Value | B11: =B9 -> 141800712420
A12: Less: Debt | B12: ='1_Public Data Inputs'!B8 -> 40710000000
A13: Add: Cash | B13: ='1_Public Data Inputs'!B9 -> 5970000000
A14: Equity Value | B14: =B11-B12+B13 -> 107060712420
A16: Shares Outstanding | B16: ='1_Public Data Inputs'!B7 -> 1340000000
A17: Implied Share Price | B17: =B14/B16 -> 79.896054

Sheet 6_Sensitivity
A1: Active WACC | B1: 0.065
A2: Active Terminal Growth | B2: 0.015
A3: Base WACC
A4: Base Terminal Growth (g) | B4: =IF('6_Sensitivity'!$B$2="",0.02,'6_Sensitivity'!$B$2) -> 0.015
A5: Base Implied Share Price | B5: ='5_DCF Valuation'!B17 -> 79.896054
D6: Terminal Growth (g)
C7: 0.015 | D7: 0.02 | E7: 0.025 | F7: 0.03
A8: WACC | B8: 0.06 | C8: =IFERROR( ( '5_DCF Valuation'!$B$3/(1+$B8)^1 + '5_DCF Valuation'!$C$3/(1+$B8)^2 + '5_DCF Valuation'!$D$3/(1+$B8)^3 + '5_DCF Valuation'!$E$3/(1+$B8)^4 + '5_DCF Valuation'!$F$3/(1+$B8)^5 + ( '5_DCF Valuation'!$F$3*(1+C$7)/( $B8 - C$7 ) ) / (1+$B8)^5 - '5_DCF Valuation'!$B$12 + '5_DCF Valuation'!$B$13 ) / '5_DCF Valuation'!$B$16, "" ) -> 103.75368 | D8: =IFERROR( ( '5_DCF Valuation'!$B$3/(1+$B8)^1 + '5_DCF Valuation'!$C$3/(1+$B8)^2 + '5_DCF Valuation'!$D$3/(1+$B8)^3 + '5_DCF Valuation'!$E$3/(1+$B8)^4 + '5_DCF Valuation'!$F$3/(1+$B8)^5 + ( '5_DCF Valuation'!$F$3*(1+D$7)/( $B8 - D$7 ) ) / (1+$B8)^5 - '5_DCF Valuation'!$B$12 + '5_DCF Valuation'!$B$13 ) / '5_DCF Valuation'!$B$16, "" ) -> 117.83611 | E8: =IFERROR( ( '5_DCF Valuation'!$B$3/(1+$B8)^1 + '5_DCF Valuation'!$C$3/(1+$B8)^2 + '5_DCF Valuation'!$D$3/(1+$B8)^3 + '5_DCF Valuation'!$E$3/(1+$B8)^4 + '5_DCF Valuation'!$F$3/(1+$B8)^5 + ( '5_DCF Valuation'!$F$3*(1+E$7)/( $B8 - E$7 ) ) / (1+$B8)^5 - '5_DCF Valuation'!$B$12 + '5_DCF Valuation'!$B$13 ) / '5_DCF Valuation'!$B$16, "" ) -> 135.94209 | F8: =IFERROR( ( '5_DCF Valuation'!$B$3/(1+$B8)^1 + '5_DCF Valuation'!$C$3/(1+$B8)^2 + '5_DCF Valuation'!$D$3/(1+$B8)^3 + '5_DCF Valuation'!$E$3/(1+$B8)^4 + '5_DCF Valuation'!$F$3/(1+$B8)^5 + ( '5_DCF Valuation'!$F$3*(1+F$7)/( $B8 - F$7 ) ) / (1+$B8)^5 - '5_DCF Valuation'!$B$12 + '5_DCF Valuation'!$B$13 ) / '5_DCF Valuation'!$B$16, "" ) -> 160.0834
B9: 0.065 | C9: =IFERROR( ( '5_DCF Valuation'!$B$3/(1+$B9)^1 + '5_DCF Valuation'!$C$3/(1+$B9)^2 + '5_DCF Valuation'!$D$3/(1+$B9)^3 + '5_DCF Valuation'!$E$3/(1+$B9)^4 + '5_DCF Valuation'!$F$3/(1+$B9)^5 + ( '5_DCF Valuation'!$F$3*(1+C$7)/( $B9 - C$7 ) ) / (1+$B9)^5 - '5_DCF Valuation'!$B$12 + '5_DCF Valuation'!$B$13 ) / '5_DCF Valuation'!$B$16, "" ) -> 90.408168 | D9: =IFERROR( ( '5_DCF Valuation'!$B$3/(1+$B9)^1 + '5_DCF Valuation'!$C$3/(1+$B9)^2 + '5_DCF Valuation'!$D$3/(1+$B9)^3 + '5_DCF Valuation'!$E$3/(1+$B9)^4 + '5_DCF Valuation'!$F$3/(1+$B9)^5 + ( '5_DCF Valuation'!$F$3*(1+D$7)/( $B9 - D$7 ) ) / (1+$B9)^5 - '5_DCF Valuation'!$B$12 + '5_DCF Valuation'!$B$13 ) / '5_DCF Valuation'!$B$16, "" ) -> 101.46403 | E9: =IFERROR( ( '5_DCF Valuation'!$B$3/(1+$B9)^1 + '5_DCF Valuation'!$C$3/(1+$B9)^2 + '5_DCF Valuation'!$D$3/(1+$B9)^3 + '5_DCF Valuation'!$E$3/(1+$B9)^4 + '5_DCF Valuation'!$F$3/(1+$B9)^5 + ( '5_DCF Valuation'!$F$3*(1+E$7)/( $B9 - E$7 ) ) / (1+$B9)^5 - '5_DCF Valuation'!$B$12 + '5_DCF Valuation'!$B$13 ) / '5_DCF Valuation'!$B$16, "" ) -> 115.28386 | F9: =IFERROR( ( '5_DCF Valuation'!$B$3/(1+$B9)^1 + '5_DCF Valuation'!$C$3/(1+$B9)^2 + '5_DCF Valuation'!$D$3/(1+$B9)^3 + '5_DCF Valuation'!$E$3/(1+$B9)^4 + '5_DCF Valuation'!$F$3/(1+$B9)^5 + ( '5_DCF Valuation'!$F$3*(1+F$7)/( $B9 - F$7 ) ) / (1+$B9)^5 - '5_DCF Valuation'!$B$12 + '5_DCF Valuation'!$B$13 ) / '5_DCF Valuation'!$B$16, "" ) -> 133.05221
B10: 0.07 | C10: =IFERROR( ( '5_DCF Valuation'!$B$3/(1+$B10)^1 + '5_DCF Valuation'!$C$3/(1+$B10)^2 + '5_DCF Valuation'!$D$3/(1+$B10)^3 + '5_DCF Valuation'!$E$3/(1+$B10)^4 + '5_DCF Valuation'!$F$3/(1+$B10)^5 + ( '5_DCF Valuation'!$F$3*(1+C$7)/( $B10 - C$7 ) ) / (1+$B10)^5 - '5_DCF Valuation'!$B$12 + '5_DCF Valuation'!$B$13 ) / '5_DCF Valuation'!$B$16, "" ) -> 79.498043 | D10: =IFERROR( ( '5_DCF Valuation'!$B$3/(1+$B10)^1 + '5_DCF Valuation'!$C$3/(1+$B10)^2 + '5_DCF Valuation'!$D$3/(1+$B10)^3 + '5_DCF Valuation'!$E$3/(1+$B10)^4 + '5_DCF Valuation'!$F$3/(1+$B10)^5 + ( '5_DCF Valuation'!$F$3*(1+D$7)/( $B10 - D$7 ) ) / (1+$B10)^5 - '5_DCF Valuation'!$B$12 + '5_DCF Valuation'!$B$13 ) / '5_DCF Valuation'!$B$16, "" ) -> 88.375852 | E10: =IFERROR( ( '5_DCF Valuation'!$B$3/(1+$B10)^1 + '5_DCF Valuation'!$C$3/(1+$B10)^2 + '5_DCF Valuation'!$D$3/(1+$B10)^3 + '5_DCF Valuation'!$E$3/(1+$B10)^4 + '5_DCF Valuation'!$F$3/(1+$B10)^5 + ( '5_DCF Valuation'!$F$3*(1+E$7)/( $B10 - E$7 ) ) / (1+$B10)^5 - '5_DCF Valuation'!$B$12 + '5_DCF Valuation'!$B$13 ) / '5_DCF Valuation'!$B$16, "" ) -> 99.226507 | F10: =IFERROR( ( '5_DCF Valuation'!$B$3/(1+$B10)^1 + '5_DCF Valuation'!$C$3/(1+$B10)^2 + '5_DCF Valuation'!$D$3/(1+$B10)^3 + '5_DCF Valuation'!$E$3/(1+$B10)^4 + '5_DCF Valuation'!$F$3/(1+$B10)^5 + ( '5_DCF Valuation'!$F$3*(1+F$7)/( $B10 - F$7 ) ) / (1+$B10)^5 - '5_DCF Valuation'!$B$12 + '5_DCF Valuation'!$B$13 ) / '5_DCF Valuation'!$B$16, "" ) -> 112.78983
B11: 0.075 | C11: =IFERROR( ( '5_DCF Valuation'!$B$3/(1+$B11)^1 + '5_DCF Valuation'!$C$3/(1+$B11)^2 + '5_DCF Valuation'!$D$3/(1+$B11)^3 + '5_DCF Valuation'!$E$3/(1+$B11)^4 + '5_DCF Valuation'!$F$3/(1+$B11)^5 + ( '5_DCF Valuation'!$F$3*(1+C$7)/( $B11 - C$7 ) ) / (1+$B11)^5 - '5_DCF Valuation'!$B$12 + '5_DCF Valuation'!$B$13 ) / '5_DCF Valuation'!$B$16, "" ) -> 70.414208 | D11: =IFERROR( ( '5_DCF Valuation'!$B$3/(1+$B11)^1 + '5_DCF Valuation'!$C$3/(1+$B11)^2 + '5_DCF Valuation'!$D$3/(1+$B11)^3 + '5_DCF Valuation'!$E$3/(1+$B11)^4 + '5_DCF Valuation'!$F$3/(1+$B11)^5 + ( '5_DCF Valuation'!$F$3*(1+D$7)/( $B11 - D$7 ) ) / (1+$B11)^5 - '5_DCF Valuation'!$B$12 + '5_DCF Valuation'!$B$13 ) / '5_DCF Valuation'!$B$16, "" ) -> 77.675699 | E11: =IFERROR( ( '5_DCF Valuation'!$B$3/(1+$B11)^1 + '5_DCF Valuation'!$C$3/(1+$B11)^2 + '5_DCF Valuation'!$D$3/(1+$B11)^3 + '5_DCF Valuation'!$E$3/(1+$B11)^4 + '5_DCF Valuation'!$F$3/(1+$B11)^5 + ( '5_DCF Valuation'!$F$3*(1+E$7)/( $B11 - E$7 ) ) / (1+$B11)^5 - '5_DCF Valuation'!$B$12 + '5_DCF Valuation'!$B$13 ) / '5_DCF Valuation'!$B$16, "" ) -> 86.389489 | F11: =IFERROR( ( '5_DCF Valuation'!$B$3/(1+$B11)^1 + '5_DCF Valuation'!$C$3/(1+$B11)^2 + '5_DCF Valuation'!$D$3/(1+$B11)^3 + '5_DCF Valuation'!$E$3/(1+$B11)^4 + '5_DCF Valuation'!$F$3/(1+$B11)^5 + ( '5_DCF Valuation'!$F$3*(1+F$7)/( $B11 - F$7 ) ) / (1+$B11)^5 - '5_DCF Valuation'!$B$12 + '5_DCF Valuation'!$B$13 ) / '5_DCF Valuation'!$B$16, "" ) -> 97.039676
B12: 0.08 | C12: =IFERROR( ( '5_DCF Valuation'!$B$3/(1+$B12)^1 + '5_DCF Valuation'!$C$3/(1+$B12)^2 + '5_DCF Valuation'!$D$3/(1+$B12)^3 + '5_DCF Valuation'!$E$3/(1+$B12)^4 + '5_DCF Valuation'!$F$3/(1+$B12)^5 + ( '5_DCF Valuation'!$F$3*(1+C$7)/( $B12 - C$7 ) ) / (1+$B12)^5 - '5_DCF Valuation'!$B$12 + '5_DCF Valuation'!$B$13 ) / '5_DCF Valuation'!$B$16, "" ) -> 62.734993 | D12: =IFERROR( ( '5_DCF Valuation'!$B$3/(1+$B12)^1 + '5_DCF Valuation'!$C$3/(1+$B12)^2 + '5_DCF Valuation'!$D$3/(1+$B12)^3 + '5_DCF Valuation'!$E$3/(1+$B12)^4 + '5_DCF Valuation'!$F$3/(1+$B12)^5 + ( '5_DCF Valuation'!$F$3*(1+D$7)/( $B12 - D$7 ) ) / (1+$B12)^5 - '5_DCF Valuation'!$B$12 + '5_DCF Valuation'!$B$13 ) / '5_DCF Valuation'!$B$16, "" ) -> 68.766335 | E12: =IFERROR( ( '5_DCF Valuation'!$B$3/(1+$B12)^1 + '5_DCF Valuation'!$C$3/(1+$B12)^2 + '5_DCF Valuation'!$D$3/(1+$B12)^3 + '5_DCF Valuation'!$E$3/(1+$B12)^4 + '5_DCF Valuation'!$F$3/(1+$B12)^5 + ( '5_DCF Valuation'!$F$3*(1+E$7)/( $B12 - E$7 ) ) / (1+$B12)^5 - '5_DCF Valuation'!$B$12 + '5_DCF Valuation'!$B$13 ) / '5_DCF Valuation'!$B$16, "" ) -> 75.894285 | F12: =IFERROR( ( '5_DCF Valuation'!$B$3/(1+$B12)^1 + '5_DCF Valuation'!$C$3/(1+$B12)^2 + '5_DCF Valuation'!$D$3/(1+$B12)^3 + '5_DCF Valuation'!$E$3/(1+$B12)^4 + '5_DCF Valuation'!$F$3/(1+$B12)^5 + ( '5_DCF Valuation'!$F$3*(1+F$7)/( $B12 - F$7 ) ) / (1+$B12)^5 - '5_DCF Valuation'!$B$12 + '5_DCF Valuation'!$B$13 ) / '5_DCF Valuation'!$B$16, "" ) -> 84.447825

Sheet 7_Scenarios
A1: Active Scenario | B1: Base / Upside / Downside
A2: Selector | B2: Base
A4: Input | B4: Base Case | C4: Upside | D4: Downside
A5: Scenario Name | B5: Base Case | C5: Defense / Geopolitical Upside | D5: Cost Pressure / High Rate Enviroment
A7: Revenue Growth | B7: 0.06 | C7: 0.065 | D7: 0.025
A8: EBIT Margin | B8: 0.103 | C8: 0.115 | D8: 0.097
A9: WACC | B9: 0.0698 | C9: 0.063 | D9: 0.0775
A10: Terminal Growth (g) | B10: 0.015 | C10: 0.02 | D10: 0.01
A11: CapEx % of Revenue | B11: 0.03 | C11: 0.032 | D11: 0.035

Sheet 8_Notes and Sources
A1: Yahoo Finance – Price, Market Cap, Beta, EV
A2: RTX 10-K – Revenue mix, margins
A3: RTX Investor Presentation – Backlog & contract exposure
A4: FRED – Risk-free rate
A5: FinViz / Morningstar – Peer multiples
A7: Share Price → https://finance.yahoo.com/quote/RTX
A8: Market Cap → Yahoo Finance – RTX summary
A9: Enterprise Value → Yahoo Finance – Statistics
A10: Total Debt & Cash → Yahoo Finance – Balance Sheet
A11: Revenue & EBIT → Yahoo Finance – Financials
A12: Beta → Yahoo Finance – Statistics
A13: 10Y Treasury Yield → https://fred.stlouisfed.org/series/DGS10
